<Properties StartupConfiguration="{7A0E406D-966A-4461-9B56-13F73640040A}|Default">
  <MonoDevelop.Ide.Workbench ActiveDocument="Assignment/wwwroot/css/site.css">
    <Files>
      <File FileName="Assignment/Program.cs" Line="1" Column="1" />
      <File FileName="Assignment/Startup.cs" Line="1" Column="1" />
      <File FileName="Assignment/wwwroot/css/site.css" Line="1" Column="1" />
    </Files>
    <Pads>
      <Pad Id="ProjectPad">
        <State name="__root__">
          <Node name="Assignment" expanded="True">
            <Node name="Assignment" expanded="True">
              <Node name="Properties" expanded="True" />
              <Node name="wwwroot" expanded="True">
                <Node name="css" expanded="True">
                  <Node name="site.css" selected="True" />
                </Node>
                <Node name="js" expanded="True" />
              </Node>
              <Node name="appsettings.json" expanded="True" />
            </Node>
          </Node>
        </State>
      </Pad>
    </Pads>
  </MonoDevelop.Ide.Workbench>
  <MonoDevelop.Ide.ItemProperties.Assignment PreferredExecutionTarget="/Applications/Safari.app" />
  <MonoDevelop.Ide.DebuggingService.PinnedWatches />
  <MonoDevelop.Ide.Workspace ActiveConfiguration="Debug" />
  <MonoDevelop.Ide.DebuggingService.Breakpoints>
    <BreakpointStore />
  </MonoDevelop.Ide.DebuggingService.Breakpoints>
  <MultiItemStartupConfigurations />
</Properties>